consolcolor.py
consolcolor-1.0.0.dist-info/METADATA
consolcolor-1.0.0.dist-info/RECORD
consolcolor-1.0.0.dist-info/WHEEL
consolcolor-1.0.0.dist-info/entry_points.txt
consolcolor-1.0.0.dist-info/top_level.txt
