Metadata-Version: 2.1
Name: consolcolor
Version: 1.0.0
Summary: Simple Todoconsol Program
Home-page: https://github.com/SonMinWoo/AnsanBladeWind
Author: Ansan Blade Wind
Author-email: hun97106@naver.com
License: MIT
Download-URL: https://github.com/SonMinWoo/AnsanBladeWind/archive/todoconsol-0.1.tar.gz
Keywords: todoconsol,task manager
Platform: UNKNOWN
Classifier: Programming Language :: Python :: 3
Classifier: Programming Language :: Python :: 3.2
Classifier: Programming Language :: Python :: 3.3
Classifier: Programming Language :: Python :: 3.4
Classifier: Programming Language :: Python :: 3.5
Classifier: Programming Language :: Python :: 3.6
Requires-Python: >=3
